LICENSE
README.md
extended_enum/__init__.py
extended_enum/tools.py
extended_enum-1.1.0.dist-info/LICENSE
extended_enum-1.1.0.dist-info/METADATA
extended_enum-1.1.0.dist-info/WHEEL
extended_enum-1.1.0.dist-info/RECORD
