Metadata-Version: 2.1
Name: extended-enum
Version: 1.1.0
Summary: Extends the capabilities of the standard Enum.
Home-page: https://github.com/ilichev-andrey/python-extended-enum
License: Apache-2.0
Keywords: enum,extended,extended-enum
Author: Ilichev Andrey
Author-email: ilichev.andrey.y@gmail.com
Requires-Python: >=3.8.1,<4.0.0
Classifier: License :: OSI Approved :: Apache Software License
Classifier: Operating System :: OS Independent
Classifier: Programming Language :: Python
Classifier: Programming Language :: Python :: 3
Classifier: Programming Language :: Python :: 3.9
Classifier: Programming Language :: Python :: 3.10
Classifier: Programming Language :: Python :: 3.11
Classifier: Programming Language :: Python :: 3.12
Classifier: Programming Language :: Python :: 3 :: Only
Classifier: Programming Language :: Python :: 3.8
Project-URL: Documentation, https://github.com/ilichev-andrey/python-extended-enum
Project-URL: Repository, https://github.com/ilichev-andrey/python-extended-enum
Project-URL: Tracker, https://github.com/ilichev-andrey/python-extended-enum/issues
